bs_common_fastapi_mongodb/__init__.py
bs_common_fastapi_mongodb/common/__init__.py
bs_common_fastapi_mongodb/common/application/__init__.py
bs_common_fastapi_mongodb/common/application/base.py
bs_common_fastapi_mongodb/common/config/__init__.py
bs_common_fastapi_mongodb/common/config/base.py
bs_common_fastapi_mongodb/common/dependencies/__init__.py
bs_common_fastapi_mongodb/common/dependencies/base.py
bs_common_fastapi_mongodb/common/model/__init__.py
bs_common_fastapi_mongodb/common/model/base_default_model.py
bs_common_fastapi_mongodb-0.2.4.dist-info/METADATA
bs_common_fastapi_mongodb-0.2.4.dist-info/WHEEL
bs_common_fastapi_mongodb-0.2.4.dist-info/RECORD
