Metadata-Version: 2.1
Name: bs-common-fastapi-mongodb
Version: 0.2.4
Summary: 
Author: Bruno Segato
Author-email: brunosegatoit@gmail.com
Requires-Python: >=3.11,<4.0
Classifier: Programming Language :: Python :: 3
Classifier: Programming Language :: Python :: 3.11
Requires-Dist: bs-common-fastapi (>=0.3.3,<0.4.0)
Requires-Dist: motor (>=3.1.2,<4.0.0)
